LICENSE
stratosphere/__init__.py
stratosphere/config.py
stratosphere/experiment.py
stratosphere/job.py
stratosphere/run.py
stratosphere/store/__init__.py
stratosphere/store/db/__init__.py
stratosphere/store/db/database.py
stratosphere/store/db/models.py
stratosphere/store/frames.py
stratosphere/store/serialization.py
stratosphere/stratosphere.py
stratosphere/utils/__init__.py
stratosphere/utils/assertions.py
stratosphere/utils/dask.py
stratosphere/utils/dicts.py
stratosphere/utils/enums.py
stratosphere/utils/environment.py
stratosphere/utils/log.py
stratosphere/utils/metrics.py
stratosphere/utils/profiling.py
stratosphere/utils/progress.py
stratosphere/utils/sequence.py
stratosphere/utils/text.py
stratosphere/utils/time.py
stratosphere/utils/widgets.py
stratosphere-0.1.68.dist-info/LICENSE
stratosphere-0.1.68.dist-info/WHEEL
stratosphere-0.1.68.dist-info/METADATA
stratosphere-0.1.68.dist-info/RECORD
