Metadata-Version: 2.1
Name: stratosphere
Version: 0.1.68
Summary: A lightweight experimentation toolkit for data scientists.
Home-page: https://github.com/elehcimd/stratosphere
License: BSD-3
Author: Michele Dallachiesa
Author-email: michele.dallachiesa@sigforge.com
Requires-Python: >=3.8.0,<3.11
Classifier: Development Status :: 3 - Alpha
Classifier: Intended Audience :: Science/Research
Classifier: License :: OSI Approved
Classifier: License :: Other/Proprietary License
Classifier: Programming Language :: Python :: 3
Classifier: Programming Language :: Python :: 3.8
Classifier: Programming Language :: Python :: 3.9
Classifier: Programming Language :: Python :: 3.10
Provides-Extra: complete
Provides-Extra: dask
Provides-Extra: pgsql
Requires-Dist: cloudpickle (>=2.2.0,<3.0.0)
Requires-Dist: colorama (>=0.4.6,<0.5.0)
Requires-Dist: dask[complete] (>=2022.11.0,<2023.0.0); extra == "dask" or extra == "complete"
Requires-Dist: ipywidgets (>=8.0.2,<9.0.0); extra == "complete"
Requires-Dist: joblib (>=1.2.0,<2.0.0)
Requires-Dist: pandas (>=1.5.1,<2.0.0)
Requires-Dist: psycopg2-binary (>=2.9.5,<3.0.0); extra == "pgsql"
Requires-Dist: scikit-learn (>=1.1.3,<2.0.0); extra == "complete"
Requires-Dist: sqlalchemy (>=1.4.44,<2.0.0)
Requires-Dist: sqlalchemy-utils (>=0.38.3,<0.39.0)
Requires-Dist: tabulate (>=0.9.0,<0.10.0); extra == "complete"
Requires-Dist: tqdm (>=4.64.1,<5.0.0)
Requires-Dist: ulid-py (>=1.1.0,<2.0.0)
Project-URL: Repository, https://github.com/elehcimd/stratosphere
